backlogapi/__init__.py
backlogapi/backlogclient.py
backlogapi/exceptions.py
backlogapi/utilities.py
backlogapi/version.py
backlogapi/resourse/__init__.py
backlogapi/resourse/base.py
backlogapi/resourse/group.py
backlogapi/resourse/issue.py
backlogapi/resourse/notification.py
backlogapi/resourse/project.py
backlogapi/resourse/pullreqest.py
backlogapi/resourse/repository.py
backlogapi/resourse/shared_file.py
backlogapi/resourse/space.py
backlogapi/resourse/star.py
backlogapi/resourse/user.py
backlogapi/resourse/webhook.py
backlogapi/resourse/wiki.py
backlogapi-0.1.5.dist-info/LICENSE.txt
backlogapi-0.1.5.dist-info/METADATA
backlogapi-0.1.5.dist-info/RECORD
backlogapi-0.1.5.dist-info/WHEEL
backlogapi-0.1.5.dist-info/top_level.txt
