Metadata-Version: 2.1
Name: backlogapi
Version: 0.1.5
Summary: Backlog client library for Python
Home-page: https://github.com/keinuma/backlogapi
Author: Keisuke Numata
Author-email: nununu.mono@gmail.com
License: MIT
Keywords: backlog backlogapi library
Platform: UNKNOWN
Classifier: Development Status :: 1 - Planning
Classifier: License :: OSI Approved :: Python Software Foundation License
Classifier: Programming Language :: Python
Classifier: Topic :: Software Development
Classifier: Intended Audience :: Developers
Classifier: Natural Language :: Japanese
Classifier: License :: OSI Approved :: MIT License
Classifier: Programming Language :: Python
Classifier: Programming Language :: Python :: 3
Classifier: Programming Language :: Python :: 3.6
Requires-Dist: certifi (==2018.4.16)
Requires-Dist: chardet (==3.0.4)
Requires-Dist: idna (==2.6)
Requires-Dist: pkginfo (==1.4.2)
Requires-Dist: pluggy (==0.6.0)
Requires-Dist: py (==1.5.3)
Requires-Dist: requests-toolbelt (==0.8.0)
Requires-Dist: requests (==2.18.4)
Requires-Dist: six (==1.11.0)
Requires-Dist: tox (==3.0.0)
Requires-Dist: tqdm (==4.23.3)
Requires-Dist: twine (==1.11.0)
Requires-Dist: urllib3 (==1.22)
Requires-Dist: virtualenv (==15.2.0)
